Workbook

Sheet Instructions
A1: User Acceptance Testing (UAT) - AI-Powered E-Commerce Platform
A3: Purpose | B3: Check that the base shop (cart, checkout, payments, admin) and the five AI agents work correctly BEFORE final submission. Every test is a small task with a clear expected result.
A4: Live shop | B4: https://testv3.websitedemolynk.com/discountv2/
A5: Agent service | B5: https://ai-agents-service-tdhq.onrender.com
A6: How to use | B6: 1) Work through the 'UAT Checklist' sheet from top to bottom. 2) Do the Steps, compare with the Expected result. 3) Choose a Status. 4) Write what actually happened. 5) Fix any Fail, then run that test again. 6) Watch the 'Summary' sheet for progress.
A7: Cells you fill in | B7: Only the yellow cells on the 'UAT Checklist' sheet: Status (column G, dropdown), Actual result / notes (column H) and Tested on (column I). Everything else is fixed.
A8: Example of a filled row | B8: Status = Pass | Actual result = 'Cart total showed Rs 25,100 after setting DALDA quantity to 8' | Tested on = 2026-10-15
A9: Status meanings | B9: Not run = not tested yet. Pass = result matched. Fail = result did not match (describe it). Blocked = could not test (e.g. missing key or access).
A10: Priority meanings | B10: High = must pass before submission. Medium = should pass. Low = nice to have.
A11: Exit criteria | B11: Ready for submission when every High priority test is Pass. The Summary sheet shows this automatically.
A12: Test safely | B12: Use test customers and test products. Use example email addresses you control. Never share API keys, screenshots showing keys, or real customer data.
A13: Known gap to fix | B13: GET /fraud/flagged, GET /fraud/history and POST /fraud/check do not require a key yet (test SEC-06). Add key protection before the final submission.
A15: Rules being tested
A16: Fraud (Agent 4) | B16: Order is Flagged at 50 risk points or more. COD above Rs 20,000 adds 25. 3 or more orders in 10 minutes from one email adds 30. Source: settings at the top of app/agents/fraud_agent.py.
A17: Refund (Agent 1) | B17: Auto-approve: not yet delivered + COD, or delivered within 24 hours and Rs 5,000 or less. Admin decides: bigger amounts, 24 hours to 7 days, unclear messages. Auto-reject: more than 7 days. 'Delivered' means the WooCommerce status Completed. Source: app/agents/refund_agent.py.
A18: Search (Agent 2) | B18: Budget words (under, below, above, 3k) are applied per product. Up to 20 smart searches per minute per visitor. Results are kept for 10 minutes. Source: app/agents/discovery_agent.py and the search snippet.
A19: Onboarding (Agent 5) | B19: Description 60 to 250 words, SEO title up to 60 characters, meta description 110 to 160, 3 to 10 tags, up to 3 attempts. Source: app/agents/onboarding_agent.py.
A20: Pricing (Agent 3) | B20: At least 2 stores needed, up to 3 search rounds, within 5% of the median = keep, at most 15% change, rounded to Rs 5. Source: app/agents/pricing_agent.py.

Sheet UAT Checklist
A1: UAT Checklist
A2: Fill the yellow columns (Status, Actual result / notes, Tested on). Example: Pass | Cart total showed Rs 25,100 | 2026-10-15
A4: ID | B4: Area | C4: Test case | D4: Steps | E4: Expected result | F4: Priority | G4: Status | H4: Actual result / notes | I4: Tested on
A5: CART-01 | B5: Cart | C5: Add a simple product to the cart | D5: Open the shop. Click Add to cart on BESAN 500gm. | E5: Cart icon shows 1 item. Cart total is Rs 100. | F5: High | G5: Not run
A6: CART-02 | B6: Cart | C6: Add a pack-size (variable) product | D6: Open DALDA BANASPATI GHEE. Choose the 5 kg Pouch Carton pack and add it to the cart. | E6: Cart shows the chosen pack size and Rs 3,125 per unit. | F6: High | G6: Not run
A7: CART-03 | B7: Cart | C7: Change the quantity | D7: In the cart, set the DALDA quantity to 8. | E7: Line total is Rs 25,000 and the cart total updates (Rs 25,100 with 1 BESAN). | F7: High | G7: Not run
A8: CART-04 | B8: Cart | C8: Remove an item | D8: Click the bin icon next to one item. | E8: The item disappears and totals are recalculated. | F8: Medium | G8: Not run
A9: CART-05 | B9: Cart | C9: Empty cart | D9: Remove every item from the cart. | E9: An empty-cart message appears and the cart icon shows Rs 0. | F9: Medium | G9: Not run
A10: CART-06 | B10: Cart | C10: Cart survives a page refresh | D10: Add an item, then refresh the page and open another page. | E10: The item is still in the cart. | F10: Medium | G10: Not run
A11: CART-07 | B11: Cart | C11: Coupon codes | D11: Create a test coupon in WooCommerce > Marketing > Coupons. Apply it in the cart, then try a wrong code. | E11: The valid coupon reduces the total. The wrong code shows a clear error. | F11: Low | G11: Not run
A12: CART-08 | B12: Cart | C12: Out-of-stock product cannot be bought | D12: Set a product to Out of stock in the admin. Open it in the shop. | E12: Add to cart is disabled or says Out of stock. | F12: Medium | G12: Not run
A13: CART-09 | B13: Cart | C13: Cart is usable on a phone | D13: Open the cart at phone width (browser dev tools or a real phone). | E13: Layout is readable, buttons are tappable, nothing overlaps. | F13: Low | G13: Not run
A14: CHK-01 | B14: Checkout | C14: Guest checkout with Cash on Delivery | D14: Add a product, go to checkout, fill every field, choose Cash on delivery, click Place Order. | E14: Thank-you page shows the order number, total and payment method Cash on delivery. | F14: High | G14: Not run
A15: CHK-02 | B15: Checkout | C15: Required fields are checked | D15: On checkout, leave the email empty and click Place Order. | E15: A clear error is shown and no order is created. | F15: High | G15: Not run
A16: CHK-03 | B16: Checkout | C16: Order summary matches the cart | D16: Compare the checkout Order summary with the cart. | E16: Items, quantities and total are identical. | F16: High | G16: Not run
... A107: DEP-07 | B107: Deployment | C107: Shop stays fast with agents installed | D107: Open the shop, search once and place an order, watching the speed. | E107: No noticeable delay for customers beyond the first request after idle. | F107: Low | G107: Not run

Sheet Summary
A1: UAT Summary (updates automatically)
A3: Area | B3: Total | C3: Pass | D3: Fail | E3: Blocked | F3: Not run | G3: % Passed
A4: Cart | B4: =COUNTIFS('UAT Checklist'!$B$5:$B$107,$A4) -> 9 | C4: =COUNTIFS('UAT Checklist'!$B$5:$B$107,$A4,'UAT Checklist'!$G$5:$G$107,"Pass") -> 0 | D4: =COUNTIFS('UAT Checklist'!$B$5:$B$107,$A4,'UAT Checklist'!$G$5:$G$107,"Fail") -> 0 | E4: =COUNTIFS('UAT Checklist'!$B$5:$B$107,$A4,'UAT Checklist'!$G$5:$G$107,"Blocked") -> 0 | F4: =B4-C4-D4-E4 -> 9 | G4: =IF(B4=0,0,C4/B4) -> 0
A5: Checkout | B5: =COUNTIFS('UAT Checklist'!$B$5:$B$107,$A5) -> 9 | C5: =COUNTIFS('UAT Checklist'!$B$5:$B$107,$A5,'UAT Checklist'!$G$5:$G$107,"Pass") -> 0 | D5: =COUNTIFS('UAT Checklist'!$B$5:$B$107,$A5,'UAT Checklist'!$G$5:$G$107,"Fail") -> 0 | E5: =COUNTIFS('UAT Checklist'!$B$5:$B$107,$A5,'UAT Checklist'!$G$5:$G$107,"Blocked") -> 0 | F5: =B5-C5-D5-E5 -> 9 | G5: =IF(B5=0,0,C5/B5) -> 0
A6: Payments | B6: =COUNTIFS('UAT Checklist'!$B$5:$B$107,$A6) -> 6 | C6: =COUNTIFS('UAT Checklist'!$B$5:$B$107,$A6,'UAT Checklist'!$G$5:$G$107,"Pass") -> 0 | D6: =COUNTIFS('UAT Checklist'!$B$5:$B$107,$A6,'UAT Checklist'!$G$5:$G$107,"Fail") -> 0 | E6: =COUNTIFS('UAT Checklist'!$B$5:$B$107,$A6,'UAT Checklist'!$G$5:$G$107,"Blocked") -> 0 | F6: =B6-C6-D6-E6 -> 6 | G6: =IF(B6=0,0,C6/B6) -> 0
A7: Admin | B7: =COUNTIFS('UAT Checklist'!$B$5:$B$107,$A7) -> 9 | C7: =COUNTIFS('UAT Checklist'!$B$5:$B$107,$A7,'UAT Checklist'!$G$5:$G$107,"Pass") -> 0 | D7: =COUNTIFS('UAT Checklist'!$B$5:$B$107,$A7,'UAT Checklist'!$G$5:$G$107,"Fail") -> 0 | E7: =COUNTIFS('UAT Checklist'!$B$5:$B$107,$A7,'UAT Checklist'!$G$5:$G$107,"Blocked") -> 0 | F7: =B7-C7-D7-E7 -> 9 | G7: =IF(B7=0,0,C7/B7) -> 0
A8: Agent 4 Fraud | B8: =COUNTIFS('UAT Checklist'!$B$5:$B$107,$A8) -> 7 | C8: =COUNTIFS('UAT Checklist'!$B$5:$B$107,$A8,'UAT Checklist'!$G$5:$G$107,"Pass") -> 0 | D8: =COUNTIFS('UAT Checklist'!$B$5:$B$107,$A8,'UAT Checklist'!$G$5:$G$107,"Fail") -> 0 | E8: =COUNTIFS('UAT Checklist'!$B$5:$B$107,$A8,'UAT Checklist'!$G$5:$G$107,"Blocked") -> 0 | F8: =B8-C8-D8-E8 -> 7 | G8: =IF(B8=0,0,C8/B8) -> 0
A9: Agent 1 Refund | B9: =COUNTIFS('UAT Checklist'!$B$5:$B$107,$A9) -> 13 | C9: =COUNTIFS('UAT Checklist'!$B$5:$B$107,$A9,'UAT Checklist'!$G$5:$G$107,"Pass") -> 0 | D9: =COUNTIFS('UAT Checklist'!$B$5:$B$107,$A9,'UAT Checklist'!$G$5:$G$107,"Fail") -> 0 | E9: =COUNTIFS('UAT Checklist'!$B$5:$B$107,$A9,'UAT Checklist'!$G$5:$G$107,"Blocked") -> 0 | F9: =B9-C9-D9-E9 -> 13 | G9: =IF(B9=0,0,C9/B9) -> 0
A10: Agent 2 Search | B10: =COUNTIFS('UAT Checklist'!$B$5:$B$107,$A10) -> 12 | C10: =COUNTIFS('UAT Checklist'!$B$5:$B$107,$A10,'UAT Checklist'!$G$5:$G$107,"Pass") -> 0 | D10: =COUNTIFS('UAT Checklist'!$B$5:$B$107,$A10,'UAT Checklist'!$G$5:$G$107,"Fail") -> 0 | E10: =COUNTIFS('UAT Checklist'!$B$5:$B$107,$A10,'UAT Checklist'!$G$5:$G$107,"Blocked") -> 0 | F10: =B10-C10-D10-E10 -> 12 | G10: =IF(B10=0,0,C10/B10) -> 0
A11: Agent 5 Onboarding | B11: =COUNTIFS('UAT Checklist'!$B$5:$B$107,$A11) -> 11 | C11: =COUNTIFS('UAT Checklist'!$B$5:$B$107,$A11,'UAT Checklist'!$G$5:$G$107,"Pass") -> 0 | D11: =COUNTIFS('UAT Checklist'!$B$5:$B$107,$A11,'UAT Checklist'!$G$5:$G$107,"Fail") -> 0 | E11: =COUNTIFS('UAT Checklist'!$B$5:$B$107,$A11,'UAT Checklist'!$G$5:$G$107,"Blocked") -> 0 | F11: =B11-C11-D11-E11 -> 11 | G11: =IF(B11=0,0,C11/B11) -> 0
A12: Agent 3 Pricing | B12: =COUNTIFS('UAT Checklist'!$B$5:$B$107,$A12) -> 12 | C12: =COUNTIFS('UAT Checklist'!$B$5:$B$107,$A12,'UAT Checklist'!$G$5:$G$107,"Pass") -> 0 | D12: =COUNTIFS('UAT Checklist'!$B$5:$B$107,$A12,'UAT Checklist'!$G$5:$G$107,"Fail") -> 0 | E12: =COUNTIFS('UAT Checklist'!$B$5:$B$107,$A12,'UAT Checklist'!$G$5:$G$107,"Blocked") -> 0 | F12: =B12-C12-D12-E12 -> 12 | G12: =IF(B12=0,0,C12/B12) -> 0
A13: Security | B13: =COUNTIFS('UAT Checklist'!$B$5:$B$107,$A13) -> 8 | C13: =COUNTIFS('UAT Checklist'!$B$5:$B$107,$A13,'UAT Checklist'!$G$5:$G$107,"Pass") -> 0 | D13: =COUNTIFS('UAT Checklist'!$B$5:$B$107,$A13,'UAT Checklist'!$G$5:$G$107,"Fail") -> 0 | E13: =COUNTIFS('UAT Checklist'!$B$5:$B$107,$A13,'UAT Checklist'!$G$5:$G$107,"Blocked") -> 0 | F13: =B13-C13-D13-E13 -> 8 | G13: =IF(B13=0,0,C13/B13) -> 0
A14: Deployment | B14: =COUNTIFS('UAT Checklist'!$B$5:$B$107,$A14) -> 7 | C14: =COUNTIFS('UAT Checklist'!$B$5:$B$107,$A14,'UAT Checklist'!$G$5:$G$107,"Pass") -> 0 | D14: =COUNTIFS('UAT Checklist'!$B$5:$B$107,$A14,'UAT Checklist'!$G$5:$G$107,"Fail") -> 0 | E14: =COUNTIFS('UAT Checklist'!$B$5:$B$107,$A14,'UAT Checklist'!$G$5:$G$107,"Blocked") -> 0 | F14: =B14-C14-D14-E14 -> 7 | G14: =IF(B14=0,0,C14/B14) -> 0
A15: TOTAL | B15: =SUM(B4:B14) -> 103 | C15: =SUM(C4:C14) -> 0 | D15: =SUM(D4:D14) -> 0 | E15: =SUM(E4:E14) -> 0 | F15: =SUM(F4:F14) -> 103 | G15: =IF(B15=0,0,C15/B15) -> 0
A17: High priority tests not yet Pass | B17: =COUNTIFS('UAT Checklist'!$F$5:$F$107,"High",'UAT Checklist'!$G$5:$G$107,"<>Pass") -> 54
A18: Submission status | B18: =IF(B17=0,"READY: all High priority tests passed","NOT READY: "&B17&" High priority test(s) not passed") -> NOT READY: 54 High priority test(s) not passed

Sheet Test Data
A1: Test data to reuse
A3: Item | B3: Value | C3: Used in
A4: Product: BESAN 500gm | B4: Rs 100 (from your earlier test order) | C4: CART, CHK
A5: Product: DALDA BANASPATI GHEE, 5 kg Pouch Carton | B5: Rs 3,125 each (8 units = Rs 25,000) | C5: CART, FRD, REF
A6: Product: KISAN COOKING OIL, 5 Liter Pouch Carton | B6: Rs 2,875 each (25 units = Rs 71,875) | C6: SRCH, PRC, FRD
A7: Test customer email | B7: Use an email address you control (example: yourname+test1@gmail.com) | C7: CHK, FRD, REF
A8: Search: budget | B8: cooking oil under 3000 | C8: SRCH
A9: Search: two items | B9: cooking oil and ghee under 4000 | C9: SRCH
A10: Search: mixed language | B10: ghee aur oil under 4000 | C10: SRCH
A11: Search: no match | B11: zzzzqqq | C11: SRCH
A12: Refund message: damaged | B12: The ghee carton arrived damaged, I want my money back | C12: REF
A13: Refund message: cancel | B13: Please cancel my order | C13: REF
A14: Refund message: unclear | B14: what is your phone number | C14: REF
... A19: Agent service test page | B19: https://ai-agents-service-tdhq.onrender.com/docs | C19: FRD, REF, SEC, DEP
A21: Product names and prices come from your earlier test orders; replace them if your catalog changes.
